hobby.py
hobby-1.0.0.dist-info/LICENSE
hobby-1.0.0.dist-info/METADATA
hobby-1.0.0.dist-info/WHEEL
hobby-1.0.0.dist-info/top_level.txt
hobby-1.0.0.dist-info/RECORD
