Metadata-Version: 2.1
Name: hobby
Version: 1.0.0
Summary: Desenvolvimento fácil e rápido de jogos 2D simples.
Author: José Falero
Classifier: Programming Language :: Python :: 3
Classifier: Intended Audience :: Developers
Classifier: License :: OSI Approved :: GNU General Public License v3 (GPLv3)
Classifier: Natural Language :: Portuguese (Brazilian)
Classifier: Operating System :: OS Independent
Classifier: Topic :: Software Development :: Libraries :: Python Modules
Requires-Python: >=3.9.2
License-File: LICENSE
Requires-Dist: pygame >=2.5.2
